astfriend/__init__.py
astfriend/ast_allure/__init__.py
astfriend/ast_allure/ast_allure.py
astfriend/ast_impoprts/__init__.py
astfriend/ast_impoprts/ast_imports.py
astfriend/ast_pydantic/__init__.py
astfriend/ast_pydantic/ast_pydantic.py
astfriend/ast_python/__init__.py
astfriend/ast_python/ast_class_def.py
astfriend/ast_python/ast_fun_def.py
astfriend/ast_python/ast_simpl_obj.py
astfriend/ast_python/python_keywords.py
astfriend/ast_tenacity/__init__.py
astfriend/ast_tenacity/ast_tenacity.py
astfriend/objs/__init__.py
astfriend/objs/keywords/__init__.py
astfriend/objs/keywords/ast_keywords.py
astfriend/objs/keywords/python_keywords.py
astfriend/utility/__init__.py
astfriend/utility/func_names.py
astfriend-0.1.20.dist-info/LICENSE
astfriend-0.1.20.dist-info/METADATA
astfriend-0.1.20.dist-info/WHEEL
astfriend-0.1.20.dist-info/RECORD
